"lampseek/__init__,py"
lampseek/lampseek.py
lampseek-0.0.1.dist-info/LICENSE
lampseek-0.0.1.dist-info/METADATA
lampseek-0.0.1.dist-info/WHEEL
lampseek-0.0.1.dist-info/RECORD
